{
  "stock_code": "RDDT",
  "title": "분기 실적",
  "currency": "USD",
  "value_unit": "백만$",
  "money_cols": [
    "매출",
    "매출총이익",
    "영업이익",
    "순이익",
    "영업CF",
    "FCF",
    "CAPEX"
  ],
  "unit": "단위: 백만$(USD) 3개월 기준 · 분기손익=직접(Q4=연간−3Q), 현금흐름=YTD차분 · 출처 SEC EDGAR · Q1'24 순손실은 IPO 관련 주식보상 대량 인식분($약 595M) 포함 · 흑자전환 초기라 저기저효과로 영익YoY/QoQ %가 크게 튐",
  "headers": [
    "분기",
    "매출",
    "매출YoY",
    "매출QoQ",
    "매출총이익",
    "GPM",
    "영업이익",
    "영익YoY",
    "영익QoQ",
    "OPM",
    "순이익",
    "영업CF",
    "FCF",
    "CAPEX"
  ],
  "rows": [
    [
      "Q1'24",
      "243",
      "+48.4%",
      "-2.7%",
      "215",
      "88.6%",
      "-589",
      "적자",
      "적자",
      "-242.5%",
      "-575",
      "32",
      "29",
      "3"
    ],
    [
      "Q2'24",
      "281",
      "+53.6%",
      "+15.7%",
      "252",
      "89.5%",
      "-31",
      "적자",
      "적자",
      "-11.0%",
      "-10",
      "28",
      "27",
      "1"
    ],
    [
      "Q3'24",
      "348",
      "+67.9%",
      "+23.9%",
      "314",
      "90.1%",
      "7",
      "흑전",
      "흑전",
      "2.0%",
      "30",
      "72",
      "70",
      "1"
    ],
    [
      "Q4'24",
      "428",
      "+71.3%",
      "+22.8%",
      "396",
      "92.6%",
      "53",
      "+1653.6%",
      "+671.4%",
      "12.4%",
      "71",
      "90",
      "89",
      "1"
    ],
    [
      "Q1'25",
      "392",
      "+61.5%",
      "-8.3%",
      "355",
      "90.5%",
      "4",
      "흑전",
      "-92.6%",
      "1.0%",
      "26",
      "128",
      "127",
      "1"
    ],
    [
      "Q2'25",
      "500",
      "+77.7%",
      "+27.3%",
      "454",
      "90.8%",
      "68",
      "흑전",
      "+1634.8%",
      "13.6%",
      "89",
      "111",
      "111",
      "1"
    ],
    [
      "Q3'25",
      "585",
      "+67.9%",
      "+17.1%",
      "532",
      "91.0%",
      "139",
      "+1921.3%",
      "+104.6%",
      "23.7%",
      "163",
      "185",
      "183",
      "2"
    ],
    [
      "Q4'25",
      "726",
      "+69.7%",
      "+24.1%",
      "667",
      "91.9%",
      "232",
      "+338.5%",
      "+67.3%",
      "31.9%",
      "252",
      "267",
      "264",
      "3"
    ],
    [
      "Q1'26",
      "663",
      "+69.1%",
      "-8.6%",
      "607",
      "91.5%",
      "183",
      "+4586.4%",
      "-21.1%",
      "27.6%",
      "204",
      "312",
      "311",
      "1"
    ]
  ],
  "highlight": [
    "Q1'26"
  ]
}